{
  "result": "OK",
  "data": {
    "id": "m49656661844",
    "seller": {
      "id": 370483370,
      "name": "KH",
      "photo_url": "https://static.mercdn.net/members/370483370.jpg?1575186110",
      "photo_thumbnail_url": "https://static.mercdn.net/thumb/members/370483370.jpg?1575186110",
      "register_sms_confirmation": "yes",
      "register_sms_confirmation_at": "2020-03-20 16:36:32",
      "created": 1450848994,
      "num_sell_items": 448,
      "ratings": {
        "good": 549,
        "normal": 0,
        "bad": 0
      },
      "num_ratings": 549,
      "score": 549,
      "is_official": false,
      "quick_shipper": false,
      "is_followable": true,
      "is_blocked": false,
      "star_rating_score": 5
    },
    "converted_price": {
      "price": 192900,
      "currency_code": "VND",
      "rate_updated": 1749003003
    },
    "status": "on_sale",
    "name": "ペンタブ WACOM Bamboo fun CTH-461",
    "price": 1000,
    "description": "WACOM\nBamboo fun \n型番 CTH-461\nイラスト ペンタブ バンブーファン ワコム Wacom\n\n- モデル名: Bamboo CTH-461\n- ブランド: Wacom\n- 色: ホワイト/オレンジ\n- 接続タイプ: USB\n\nタッチペン付き\nご理解頂ける方のみお願いいたします。",
    "photos": [
      "https://static.mercdn.net/item/detail/orig/photos/m49656661844_1.jpg?1748409962",
      "https://static.mercdn.net/item/detail/orig/photos/m49656661844_2.jpg?1748409962"
    ],
    "photo_paths": [
      "photos/m49656661844_1.jpg",
      "photos/m49656661844_2.jpg"
    ],
    "thumbnails": [
      "https://static.mercdn.net/c!/w=240/thumb/photos/m49656661844_1.jpg?1748409962"
    ],
    "item_category": {
      "id": 1689,
      "name": "液タブ・ペンタブ",
      "display_order": 7,
      "parent_category_id": 968,
      "parent_category_name": "タブレット",
      "root_category_id": 7,
      "root_category_name": "スマホ・タブレット・パソコン"
    },
    "item_category_ntiers": {
      "id": 1842,
      "name": "ペンタブレット本体(板タブ)",
      "display_order": 3,
      "parent_category_id": 1689,
      "parent_category_name": "液タブ・ペンタブ",
      "root_category_id": 7,
      "root_category_name": "スマホ・タブレット・パソコン",
      "brand_group_id": 1
    },
    "parent_categories_ntiers": [
      {
        "id": 7,
        "name": "スマホ・タブレット・パソコン",
        "display_order": 0
      },
      {
        "id": 968,
        "name": "タブレット",
        "display_order": 0
      },
      {
        "id": 1689,
        "name": "液タブ・ペンタブ",
        "display_order": 0
      }
    ],
    "item_condition": {
      "id": 4,
      "name": "やや傷や汚れあり",
      "subname": "目につく傷や汚れがある"
    },
    "item_brand": {
      "id": 54524,
      "name": "ワコム",
      "sub_name": "wacom"
    },
    "colors": [],
    "shipping_payer": {
      "id": 2,
      "name": "送料込み(出品者負担)",
      "code": "seller"
    },
    "shipping_method": {
      "id": 9,
      "name": "郵便（定型、定形外、書留など）",
      "is_deprecated": "no"
    },
    "shipping_from_area": {
      "id": 14,
      "name": "神奈川県"
    },
    "shipping_duration": {
      "id": 2,
      "name": "2~3日で発送",
      "min_days": 2,
      "max_days": 3
    },
    "shipping_class": {
      "id": 0,
      "fee": 0,
      "icon_id": 0,
      "pickup_fee": 0,
      "shipping_fee": 0,
      "total_fee": 0,
      "is_pickup": false
    },
    "num_likes": 0,
    "num_comments": 0,
    "registered_prices_count": 0,
    "comments": [],
    "updated": 1748409962,
    "created": 1748409962,
    "pager_id": 5665695869,
    "liked": false,
    "checksum": "54b585ab583a4fc35de013d580976395",
    "is_dynamic_shipping_fee": false,
    "application_attributes": {},
    "is_shop_item": "no",
    "hash_tags": [],
    "is_anonymous_shipping": false,
    "is_web_visible": true,
    "is_offerable": false,
    "is_organizational_user": false,
    "organizational_user_status": "",
    "is_stock_item": false,
    "is_cancelable": true,
    "shipped_by_worker": false,
    "additional_services": [],
    "has_additional_service": false,
    "has_like_list": false,
    "is_offerable_v2": true,
    "item_attributes": [
      {
        "id": "f7f186cc-a16e-474b-a7a9-ee179b5565c0",
        "text": "photo_description",
        "values": [
          {
            "id": "",
            "text": ""
          },
          {
            "id": "",
            "text": ""
          }
        ],
        "deep_facet_filterable": false,
        "show_on_ui": false
      },
      {
        "id": "b6b9be89-648c-4af9-b3fe-1b77de4833d1",
        "text": "ブランド",
        "values": [
          {
            "id": "de9af53c-56e0-5026-96ae-76299a4acf98",
            "text": "ワコム"
          }
        ],
        "deep_facet_filterable": false,
        "show_on_ui": false
      }
    ],
    "is_dismissed": false,
    "photo_descriptions": [
      "",
      ""
    ],
    "meta_title": "ペンタブ WACOM Bamboo fun CTH-461",
    "meta_subtitle": "ワコム・やや傷や汚れあり"
  },
  "meta": {}
}